timer_dict/__init__.py
timer_dict-0.2.1.dist-info/METADATA
timer_dict-0.2.1.dist-info/WHEEL
timer_dict-0.2.1.dist-info/RECORD
