Metadata-Version: 2.1
Name: timer-dict
Version: 0.2.1
Summary: A dictionary where values are removed after a certain time
License: MIT
Author: Jakob Pinterits
Author-email: jakob.pinterits@gmail.com
Requires-Python: >=3.9,<4.0
Classifier: License :: OSI Approved :: MIT License
Classifier: Programming Language :: Python :: 3
Classifier: Programming Language :: Python :: 3.9
Classifier: Programming Language :: Python :: 3.10
Classifier: Programming Language :: Python :: 3.11
